setup.py
django_run_queues/__init__.py
django_run_queues/admin.py
django_run_queues/apps.py
django_run_queues/models.py
django_run_queues/tasks.py
django_run_queues.egg-info/PKG-INFO
django_run_queues.egg-info/SOURCES.txt
django_run_queues.egg-info/dependency_links.txt
django_run_queues.egg-info/requires.txt
django_run_queues.egg-info/top_level.txt
django_run_queues/management/__init__.py
django_run_queues/management/commands/RunQueue.py
django_run_queues/management/commands/__init__.py
django_run_queues/management/commands/schedule_queues.py
django_run_queues/migrations/0001_initial.py
django_run_queues/migrations/__init__.py